Workbook
Name PatientNames: PatientsTable[Full_Name]

Sheet Patients
A1: GNOSIS THERAPY AND WELLNESS SERVICE
A4: Patient_ID | B4: First_Name | C4: Last_Name | D4: ID_Number | E4: Phone | F4: Email | G4: Address | H4: Date_Registered | I4: Full_Name
A5: P001 | B5: Kelly | C5: Smith | D5: 9001011234 | E5: 0821234567 | F5: kelly@mail.com | G5: Pretoria | H5: 46054 | I5: =TRIM(PatientsTable[[#This Row],[First_Name]]) & " " & TRIM(PatientsTable[[#This Row],[Last_Name]]) -> Kelly Smith
A6: P002 | B6: John | C6: Doe | D6: 8905055678 | E6: 0837654321 | F6: john@mail.com | G6: Johannesburg | H6: 46056 | I6: =TRIM(PatientsTable[[#This Row],[First_Name]]) & " " & TRIM(PatientsTable[[#This Row],[Last_Name]]) -> John Doe
A7: P003 | B7: Mary | C7: Johnson | D7: 9503031122 | E7: 0841112233 | F7: mary@mail.com | G7: Cape Town | H7: 46063 | I7: =TRIM(PatientsTable[[#This Row],[First_Name]]) & " " & TRIM(PatientsTable[[#This Row],[Last_Name]]) -> Mary Johnson
A8: P004 | B8: Thabo | C8: Mokoena | D8: 9103034567 | E8: 0845567788 | F8: thabo@mail.com | G8: Centurion | H8: 07/02/2026 | I8: =B8 & " " & C8 -> Thabo Mokoena
A9: P005 | B9: Ayesha | C9: Khan | D9: 9509091122 | E9: 0793344556 | F9: ayesha@mail.com | G9: Sandton | H9: 09/02/2026 | I9: =B9 & " " & C9 -> Ayesha Khan
A10: P006 | B10: Sipho | C10: Nkosi | D10: 8701017788 | E10: 0829988776 | F10: sipho@mail.com | G10: Midrand | H10: 11/02/2026 | I10: =B10 & " " & C10 -> Sipho Nkosi
A11: P007 | B11: Lerato | C11: Molefe | D11: 9302123456 | E11: 0831122334 | F11: lerato@mail.com | G11: Pretoria East | H11: 14/02/2026 | I11: =B11 & " " & C11 -> Lerato Molefe
A12: P008 | B12: Daniel | C12: Jacobs | D12: 8907072233 | E12: 0816677889 | F12: daniel@mail.com | G12: Cape Town | H12: 18/02/2026 | I12: =B12 & " " & C12 -> Daniel Jacobs
A13: P009 | B13: Kabelo | C13: Ndlovu | D13: 9403031111 | E13: 723344556 | F13: kabelo@mail.com | G13: Pretoria | H13: 20/02/2026 | I13: =B13 & " " & C13 -> Kabelo Ndlovu
A14: P010 | B14: Bianca | C14: Adams | D14: 9607072222 | E14: 0781122334 | F14: bianca@mail.com | G14: Joburg | H14: 21/02/2026 | I14: =B14 & " " & C14 -> Bianca Adams
A15: P011 | B15: Mpho | C15: Sithole | D15: 9202023333 | E15: 0824455667 | F15: mpho@mail.com | G15: Centurion | H15: 22/02/2026 | I15: =B15 & " " & C15 -> Mpho Sithole
A16: P012 | B16: Jason | C16: Petersen | D16: 8909094444 | E16: 0847788990 | F16: jason@mail.com | G16: Cape Town | H16: 23/02/2026 | I16: =B16 & " " & C16 -> Jason Petersen
A17: P013 | B17: Zanele | C17: Khumalo | D17: 9705055555 | E17: 0795566778 | F17: zanele@mail.com | G17: Durban | H17: 24/02/2026 | I17: =B17 & " " & C17 -> Zanele Khumalo
A18: P014 | B18: Ryan | C18: Daniels | D18: 9108086666 | E18: 0839988776 | F18: ryan@mail.com | G18: Midrand | H18: 25/02/2026 | I18: =B18 & " " & C18 -> Ryan Daniels
A19: P015 | B19: Fatima | C19: Ismail | D19: 9501017777 | E19: 0812233445 | F19: fatima@mail.com | G19: Sandton | H19: 26/02/2026 | I19: =B19 & " " & C19 -> Fatima Ismail
A20: P016 | B20: Sibusiso | C20: Mthembu | D20: 9306068888 | E20: 0826677889 | F20: sibu@mail.com | G20: Pretoria | H20: 27/02/2026 | I20: =B20 & " " & C20 -> Sibusiso Mthembu
A21: P017 | B21: Nicole | C21: Williams | D21: 9404049999 | E21: 0843344556 | F21: nicole@mail.com | G21: Joburg | H21: 28/02/2026 | I21: =B21 & " " & C21 -> Nicole Williams
A22: P018 | B22: Andile | C22: Zulu | D22: 9003031212 | E22: 0789988776 | F22: andile@mail.com | G22: Durban | H22: 01/03/2026 | I22: =B22 & " " & C22 -> Andile Zulu
A23: P019 | B23: Carla | C23: Ferreira | D23: 9207073434 | E23: 0725566778 | F23: carla@mail.com | G23: Cape Town | H23: 02/03/2026 | I23: =B23 & " " & C23 -> Carla Ferreira
A24: P020 | B24: Themba | C24: Dlamini | D24: 8808085656 | E24: 0832233445 | F24: themba@mail.com | G24: Pretoria | H24: 03/03/2026 | I24: =B24 & " " & C24 -> Themba Dlamini
I26: =B26 & " " & C26
I27: =B27 & " " & C27
I28: =B28 & " " & C28
I29: =B29 & " " & C29
I30: =B30 & " " & C30
I31: =B31 & " " & C31
I32: =B32 & " " & C32
I33: =B33 & " " & C33
I34: =B34 & " " & C34
I35: =B35 & " " & C35
I36: =B36 & " " & C36
I37: =B37 & " " & C37
... I203: =B203 & " " & C203

Sheet Visits
A1: Visit_ID | B1: Patient_ID | C1: Date | D1: Session_Mode | E1: Session_Category | F1: Service | G1: Notes | H1: Amount | I1: Payment_Status
A2: V001 | B2: P001 | C2: 46058 | D2: In-person | E2: Individual | F2: Anxiety | G2: Bit Late | H2: 500 | I2: Paid
A3: V002 | B3: P001 | C3: 46065 | D3: Online | E3: Individual | F3: Stress | G3: Shy | H3: 450 | I3: Paid
A4: V003 | B4: P002 | C4: 46061 | D4: Online | E4: Individual | F4: Bereavement | G4: Interesting | H4: 500 | I4: Paid
A5: V004 | B5: P003 | C5: 46068 | D5: In-person | E5: Couple | F5: Infidelity | G5: Dangerous | H5: 600 | I5: Paid
A7: V005 | B7: P001 | C7: 05/02/2026 | D7: In-person | E7: Couple | F7: Pre-Marital Counselling | G7: First session | H7: 500 | I7: Paid
A8: V006 | B8: P001 | C8: 12/02/2026 | D8: In-person | E8: Group | F8: Mediation | G8: Anxiety review | H8: 450 | I8: Paid
A9: V007 | B9: P001 | C9: 19/02/2026 | D9: In-person | E9: Group | F9: Mediation | G9: Progress check | H9: 450 | I9: Paid
A10: V008 | B10: P002 | C10: 06/02/2026 | D10: In-person | E10: Individual | F10: Stress | G10: Initial consult | H10: 500 | I10: Paid
A11: V009 | B11: P002 | C11: 20/02/2026 | D11: In-person | E11: Couple | F11: Stress | G11: Stress session | H11: 500 | I11: Unpaid
A12: V010 | B12: P003 | C12: 08/02/2026 | D12: In-person | E12: Couple | F12: Separation | G12: Nutrition discussion | H12: 600 | I12: Paid
A13: V011 | B13: P003 | C13: 15/02/2026 | D13: Online | E13: Group | F13: Coping Skills | G13: Diet adjustment | H13: 550 | I13: Paid
A14: V012 | B14: P004 | C14: 09/02/2026 | D14: Online | E14: Couple | F14: Couple Differences | G14: Trauma session | H14: 650 | I14: Paid
A15: V013 | B15: P004 | C15: 16/02/2026 | D15: Online | E15: Group | F15: Anxiety | G15: Emotional support | H15: 600 | I15: Paid
A16: V014 | B16: P005 | C16: 10/02/2026 | D16: In-person | E16: Group | F16: Trauma | G16: Initial session | H16: 500 | I16: Paid
A17: V015 | B17: P005 | C17: 17/02/2026 | D17: In-person | E17: Individual | F17: Trauma Debriefing | G17: Family discussion | H17: 450 | I17: Unpaid
A18: V016 | B18: P006 | C18: 11/02/2026 | D18: In-person | E18: Couple | F18: Trauma | G18: Anger management | H18: 550 | I18: Paid
... A35: V033 | B35: P020 | C35: 06/03/2026 | D35: In-person | E35: Group | F35: Bereavement | G35: Emotional check | H35: 500 | I35: Unpaid

Sheet Expenses
A1: Date | B1: Category | C1: Amount | D1: Notes
A2: 46054 | B2: Utilities | C2: 200 | D2: Bought online | F2: Category | G2: Total
A3: 46055 | B3: Travel | C3: 150 | D3: Car fuel | F3: Utilities | G3: =SUMIF(ExpensesTable[Category], "Utilities", ExpensesTable[Amount]) -> 200
A4: 46056 | B4: Equipment | C4: 250 | D4: Local store | F4: Miscellaneous | G4: =SUMIF(ExpensesTable[Category], "Miscellaneous", ExpensesTable[Amount]) -> 0
A5: 46058 | B5: Equipment | C5: 100 | D5: Supplies | F5: Maintanance | G5: =SUMIF(ExpensesTable[Category], "Maintanance", ExpensesTable[Amount]) -> 0
F6: Repairs | G6: =SUMIF(ExpensesTable[Category], "Repairs", ExpensesTable[Amount]) -> 0
F7: Subscription | G7: =SUMIF(ExpensesTable[Category], "Subscription", ExpensesTable[Amount]) -> 0
F8: Software | G8: =SUMIF(ExpensesTable[Category], "Software", ExpensesTable[Amount]) -> 0
F9: Travel | G9: =SUMIF(ExpensesTable[Category], "Travel", ExpensesTable[Amount]) -> 150
F10: Equipment | G10: =SUMIF(ExpensesTable[Category], "Equipment", ExpensesTable[Amount]) -> 350
F11: Total Expenses | G11: =SUM(G3:G10) -> 700
F12: Total Revenue | G12: =SUM(VisitsTable[Amount]) -> 17600
F13: Profit | G13: =SUM(G12-G11) -> 16900

Sheet Patient_File
A1: Select Patient: | B1: Kelly Smith
A3: Patient ID | B3: =IFERROR(_xlfn.XLOOKUP(B1, PatientsTable[Full_Name], PatientsTable[Patient_ID]), "") -> P001
A4: First Name | B4: =IFERROR(_xlfn.XLOOKUP(B1, PatientsTable[Full_Name], PatientsTable[First_Name]), "") -> Kelly
A5: Last Name | B5: =IFERROR(_xlfn.XLOOKUP(B1, PatientsTable[Full_Name], PatientsTable[Last_Name]), "") -> Smith
A6: ID Number | B6: =IFERROR(_xlfn.XLOOKUP(B1, PatientsTable[Full_Name], PatientsTable[ID_Number]), "") -> 9001011234
A7: Phone | B7: =IFERROR(_xlfn.XLOOKUP(B1, PatientsTable[Full_Name], PatientsTable[Phone]), "") -> 0821234567
A8: Email | B8: =IFERROR(_xlfn.XLOOKUP(B1, PatientsTable[Full_Name], PatientsTable[Email]), "") -> kelly@mail.com
A9: Address | B9: =IFERROR(_xlfn.XLOOKUP(B1, PatientsTable[Full_Name], PatientsTable[Address]), "") -> Pretoria
A10: Date Registered | B10: =IFERROR(_xlfn.XLOOKUP(B1, PatientsTable[Full_Name], PatientsTable[Date_Registered]), "") -> 46054
A12: Date | B12: Session_Mode | C12: Session_Category | D12: Service | E12: Notes | F12: Amount | G12: Payment Status
A13: {=IFERROR(_xlfn._xlws.FILTER(VisitsTable[[Date]:[Payment_Status]], VisitsTable[Patient_ID]=_xlfn.XLOOKUP(B1, PatientsTable[Full_Name], PatientsTable[Patient_ID])), "No visits")} -> 46058 | B13: In-person | C13: Individual | D13: Anxiety | E13: Bit Late | F13: 500 | G13: Paid
A14: 46065 | B14: Online | C14: Individual | D14: Stress | E14: Shy | F14: 450 | G14: Paid
A15: 05/02/2026 | B15: In-person | C15: Couple | D15: Pre-Marital Counselling | E15: First session | F15: 500 | G15: Paid
A16: 12/02/2026 | B16: In-person | C16: Group | D16: Mediation | E16: Anxiety review | F16: 450 | G16: Paid
A17: 19/02/2026 | B17: In-person | C17: Group | D17: Mediation | E17: Progress check | F17: 450 | G17: Paid

Sheet Patient_Report
A1: Select Patient: | B1: =Patient_File!B1 -> Kelly Smith
A3: Patient ID | B3: =_xlfn.XLOOKUP(B1, PatientsTable[Full_Name], PatientsTable[Patient_ID]) -> P001
A4: First Name | B4: =IFERROR(_xlfn.XLOOKUP(B1, PatientsTable[Full_Name], PatientsTable[First_Name]), "") -> Kelly
A5: Last Name | B5: =IFERROR(_xlfn.XLOOKUP(B1, PatientsTable[Full_Name], PatientsTable[Last_Name]), "") -> Smith
A6: ID Number | B6: =IFERROR(_xlfn.XLOOKUP(B1, PatientsTable[Full_Name], PatientsTable[ID_Number]), "") -> 9001011234
A7: Phone | B7: =IFERROR(_xlfn.XLOOKUP(B1, PatientsTable[Full_Name], PatientsTable[Phone]), "") -> 0821234567
A8: Email | B8: =IFERROR(_xlfn.XLOOKUP(B1, PatientsTable[Full_Name], PatientsTable[Email]), "") -> kelly@mail.com
A9: Address | B9: =IFERROR(_xlfn.XLOOKUP(B1, PatientsTable[Full_Name], PatientsTable[Address]), "") -> Pretoria
A10: Date Registered | B10: =IFERROR(_xlfn.XLOOKUP(B1, PatientsTable[Full_Name], PatientsTable[Date_Registered]), "") -> 46054
A12: Date | B12: Session_Mode | C12: Session_Category | D12: Service | E12: Notes | F12: Amount | G12: Payment Status
A13: {=IFERROR(_xlfn._xlws.FILTER(VisitsTable[[Date]:[Payment_Status]], VisitsTable[Patient_ID]=_xlfn.XLOOKUP(B1, PatientsTable[Full_Name], PatientsTable[Patient_ID])), "No visits")} -> 46058 | B13: In-person | C13: Individual | D13: Anxiety | E13: Bit Late | F13: 500 | G13: Paid
A14: 46065 | B14: Online | C14: Individual | D14: Stress | E14: Shy | F14: 450 | G14: Paid
A15: 05/02/2026 | B15: In-person | C15: Couple | D15: Pre-Marital Counselling | E15: First session | F15: 500 | G15: Paid
A16: 12/02/2026 | B16: In-person | C16: Group | D16: Mediation | E16: Anxiety review | F16: 450 | G16: Paid
A17: 19/02/2026 | B17: In-person | C17: Group | D17: Mediation | E17: Progress check | F17: 450 | G17: Paid

Sheet Dashboard
A1: Category | B1: Total
A2: Ingredients | B2: =Expenses!G3 -> 200
A3: Transport | B3: =Expenses!G9 -> 150
A4: Other | B4: =Expenses!G10 -> 350
A5: Total | B5: =Expenses!G11 -> 700

Sheet Sheet7
B2: Paid | C2: In-Person
B3: Unpaid | C3: Online
